PrintSomething.py
PrintSomething-1.0.4.dist-info/LICENSE.txt
PrintSomething-1.0.4.dist-info/METADATA
PrintSomething-1.0.4.dist-info/WHEEL
PrintSomething-1.0.4.dist-info/top_level.txt
PrintSomething-1.0.4.dist-info/RECORD
