Metadata-Version: 2.2
Name: PrintSomething
Version: 1.0.4
Summary: PrintSomething
Author: huang yi yi
Author-email: 363766687@qq.com
Requires-Python: >=3.6
License-File: LICENSE.txt
Dynamic: author
Dynamic: author-email
Dynamic: requires-python
Dynamic: summary
